{
  "docusaurus-plugin-content-docs": {
    "default": {
      "loadedVersions": [
        {
          "versionName": "current",
          "label": "Next",
          "banner": null,
          "badge": false,
          "noIndex": false,
          "className": "docs-version-current",
          "path": "/docs",
          "tagsPath": "/docs/tags",
          "editUrl": "https://github.com/facebook/docusaurus/edit/master/website/docs",
          "editUrlLocalized": "https://github.com/facebook/docusaurus/edit/master/website/i18n/en/docusaurus-plugin-content-docs/current",
          "isLast": true,
          "routePriority": -1,
          "sidebarFilePath": "/Users/wenxuan/Documents/Github/blog_site_source/sidebars.js",
          "contentPath": "/Users/wenxuan/Documents/Github/blog_site_source/docs",
          "contentPathLocalized": "/Users/wenxuan/Documents/Github/blog_site_source/i18n/en/docusaurus-plugin-content-docs/current",
          "docs": [
            {
              "unversionedId": "IIT/doc1",
              "id": "IIT/doc1",
              "title": "Introduction",
              "description": "",
              "source": "@site/docs/IIT/1_Intro.md",
              "sourceDirName": "IIT",
              "slug": "/IIT",
              "permalink": "/docs/IIT",
              "draft": false,
              "editUrl": "https://github.com/facebook/docusaurus/edit/master/website/docs/IIT/1_Intro.md",
              "tags": [],
              "version": "current",
              "sidebarPosition": 1,
              "frontMatter": {
                "id": "doc1",
                "title": "Introduction",
                "sidebar_label": "Intro",
                "slug": "/IIT"
              },
              "sidebar": "myAutogeneratedSidebar",
              "next": {
                "title": "IIT on EEG",
                "permalink": "/docs/IIT/doc2"
              }
            },
            {
              "unversionedId": "IIT/doc2",
              "id": "IIT/doc2",
              "title": "Exploring IIT Analysis on EEG Data",
              "description": "",
              "source": "@site/docs/IIT/2_EEG.md",
              "sourceDirName": "IIT",
              "slug": "/IIT/doc2",
              "permalink": "/docs/IIT/doc2",
              "draft": false,
              "editUrl": "https://github.com/facebook/docusaurus/edit/master/website/docs/IIT/2_EEG.md",
              "tags": [],
              "version": "current",
              "sidebarPosition": 2,
              "frontMatter": {
                "id": "doc2",
                "title": "Exploring IIT Analysis on EEG Data",
                "sidebar_label": "IIT on EEG"
              },
              "sidebar": "myAutogeneratedSidebar",
              "previous": {
                "title": "Intro",
                "permalink": "/docs/IIT"
              },
              "next": {
                "title": "IIT on fMRI",
                "permalink": "/docs/IIT/doc3"
              }
            },
            {
              "unversionedId": "IIT/doc3",
              "id": "IIT/doc3",
              "title": "Exploring IIT Analysis on fMRI Data",
              "description": "",
              "source": "@site/docs/IIT/3_fMRI.md",
              "sourceDirName": "IIT",
              "slug": "/IIT/doc3",
              "permalink": "/docs/IIT/doc3",
              "draft": false,
              "editUrl": "https://github.com/facebook/docusaurus/edit/master/website/docs/IIT/3_fMRI.md",
              "tags": [],
              "version": "current",
              "sidebarPosition": 3,
              "frontMatter": {
                "id": "doc3",
                "title": "Exploring IIT Analysis on fMRI Data",
                "sidebar_label": "IIT on fMRI"
              },
              "sidebar": "myAutogeneratedSidebar",
              "previous": {
                "title": "IIT on EEG",
                "permalink": "/docs/IIT/doc2"
              },
              "next": {
                "title": "Intro & Download",
                "permalink": "/docs/Quaddle"
              }
            },
            {
              "unversionedId": "Quaddle2.0/quaddle_01",
              "id": "Quaddle2.0/quaddle_01",
              "title": "",
              "description": "Quaddle2.0: A Multidimensional 3D Stimuli for Cognitive Science Research",
              "source": "@site/docs/Quaddle2.0/1_Intro.md",
              "sourceDirName": "Quaddle2.0",
              "slug": "/Quaddle",
              "permalink": "/docs/Quaddle",
              "draft": false,
              "editUrl": "https://github.com/facebook/docusaurus/edit/master/website/docs/Quaddle2.0/1_Intro.md",
              "tags": [],
              "version": "current",
              "sidebarPosition": 1,
              "frontMatter": {
                "id": "quaddle_01",
                "title": "",
                "sidebar_label": "Intro & Download",
                "slug": "/Quaddle"
              },
              "sidebar": "myAutogeneratedSidebar",
              "previous": {
                "title": "IIT on fMRI",
                "permalink": "/docs/IIT/doc3"
              },
              "next": {
                "title": "Get Start",
                "permalink": "/docs/Quaddle2.0/quaddle_02"
              }
            },
            {
              "unversionedId": "Quaddle2.0/quaddle_02",
              "id": "Quaddle2.0/quaddle_02",
              "title": "",
              "description": "Quaddle2.0: A Multidimensional 3D Stimuli for Cognitive Science Research",
              "source": "@site/docs/Quaddle2.0/2_Get_start.md",
              "sourceDirName": "Quaddle2.0",
              "slug": "/Quaddle2.0/quaddle_02",
              "permalink": "/docs/Quaddle2.0/quaddle_02",
              "draft": false,
              "editUrl": "https://github.com/facebook/docusaurus/edit/master/website/docs/Quaddle2.0/2_Get_start.md",
              "tags": [],
              "version": "current",
              "sidebarPosition": 2,
              "frontMatter": {
                "id": "quaddle_02",
                "title": "",
                "sidebar_label": "Get Start"
              },
              "sidebar": "myAutogeneratedSidebar",
              "previous": {
                "title": "Intro & Download",
                "permalink": "/docs/Quaddle"
              },
              "next": {
                "title": "Troubleshooting",
                "permalink": "/docs/Quaddle2.0/quaddle_03"
              }
            },
            {
              "unversionedId": "Quaddle2.0/quaddle_03",
              "id": "Quaddle2.0/quaddle_03",
              "title": "",
              "description": "",
              "source": "@site/docs/Quaddle2.0/3_TroubleShooting.md",
              "sourceDirName": "Quaddle2.0",
              "slug": "/Quaddle2.0/quaddle_03",
              "permalink": "/docs/Quaddle2.0/quaddle_03",
              "draft": false,
              "editUrl": "https://github.com/facebook/docusaurus/edit/master/website/docs/Quaddle2.0/3_TroubleShooting.md",
              "tags": [],
              "version": "current",
              "sidebarPosition": 3,
              "frontMatter": {
                "id": "quaddle_03",
                "title": "",
                "sidebar_label": "Troubleshooting"
              },
              "sidebar": "myAutogeneratedSidebar",
              "previous": {
                "title": "Get Start",
                "permalink": "/docs/Quaddle2.0/quaddle_02"
              },
              "next": {
                "title": "Adding Dimension",
                "permalink": "/docs/Quaddle2.0/quaddle_04"
              }
            },
            {
              "unversionedId": "Quaddle2.0/quaddle_04",
              "id": "Quaddle2.0/quaddle_04",
              "title": "",
              "description": "Adding New Dimensions to Quaddle2.0",
              "source": "@site/docs/Quaddle2.0/4_Development.md",
              "sourceDirName": "Quaddle2.0",
              "slug": "/Quaddle2.0/quaddle_04",
              "permalink": "/docs/Quaddle2.0/quaddle_04",
              "draft": false,
              "editUrl": "https://github.com/facebook/docusaurus/edit/master/website/docs/Quaddle2.0/4_Development.md",
              "tags": [],
              "version": "current",
              "sidebarPosition": 4,
              "frontMatter": {
                "id": "quaddle_04",
                "title": "",
                "sidebar_label": "Adding Dimension"
              },
              "sidebar": "myAutogeneratedSidebar",
              "previous": {
                "title": "Troubleshooting",
                "permalink": "/docs/Quaddle2.0/quaddle_03"
              },
              "next": {
                "title": "Quaddle Dimensions",
                "permalink": "/docs/Quaddle2.0/quaddle_05"
              }
            },
            {
              "unversionedId": "Quaddle2.0/quaddle_05",
              "id": "Quaddle2.0/quaddle_05",
              "title": "",
              "description": "Body",
              "source": "@site/docs/Quaddle2.0/5_DefaultQuaddles.md",
              "sourceDirName": "Quaddle2.0",
              "slug": "/Quaddle2.0/quaddle_05",
              "permalink": "/docs/Quaddle2.0/quaddle_05",
              "draft": false,
              "editUrl": "https://github.com/facebook/docusaurus/edit/master/website/docs/Quaddle2.0/5_DefaultQuaddles.md",
              "tags": [],
              "version": "current",
              "sidebarPosition": 5,
              "frontMatter": {
                "id": "quaddle_05",
                "title": "",
                "sidebar_label": "Quaddle Dimensions"
              },
              "sidebar": "myAutogeneratedSidebar",
              "previous": {
                "title": "Adding Dimension",
                "permalink": "/docs/Quaddle2.0/quaddle_04"
              },
              "next": {
                "title": "Intro",
                "permalink": "/docs/SL"
              }
            },
            {
              "unversionedId": "Sequence Learning/SL_Intro",
              "id": "Sequence Learning/SL_Intro",
              "title": "Introduction",
              "description": "",
              "source": "@site/docs/Sequence Learning/Intro.md",
              "sourceDirName": "Sequence Learning",
              "slug": "/SL",
              "permalink": "/docs/SL",
              "draft": false,
              "editUrl": "https://github.com/facebook/docusaurus/edit/master/website/docs/Sequence Learning/Intro.md",
              "tags": [],
              "version": "current",
              "frontMatter": {
                "id": "SL_Intro",
                "title": "Introduction",
                "sidebar_label": "Intro",
                "slug": "/SL"
              },
              "sidebar": "myAutogeneratedSidebar",
              "previous": {
                "title": "Quaddle Dimensions",
                "permalink": "/docs/Quaddle2.0/quaddle_05"
              },
              "next": {
                "title": "Style Guide",
                "permalink": "/docs/test/doc1"
              }
            },
            {
              "unversionedId": "test/doc1",
              "id": "test/doc1",
              "title": "Style Guide",
              "description": "You can write content using GitHub-flavored Markdown syntax.",
              "source": "@site/docs/test/doc1.md",
              "sourceDirName": "test",
              "slug": "/test/doc1",
              "permalink": "/docs/test/doc1",
              "draft": false,
              "editUrl": "https://github.com/facebook/docusaurus/edit/master/website/docs/test/doc1.md",
              "tags": [],
              "version": "current",
              "frontMatter": {
                "id": "doc1",
                "title": "Style Guide",
                "sidebar_label": "Style Guide"
              },
              "sidebar": "myAutogeneratedSidebar",
              "previous": {
                "title": "Intro",
                "permalink": "/docs/SL"
              },
              "next": {
                "title": "Document Number 2",
                "permalink": "/docs/test/doc2"
              }
            },
            {
              "unversionedId": "test/doc2",
              "id": "test/doc2",
              "title": "Document Number 2",
              "description": "This is a link to another document. This is a link to an external page.",
              "source": "@site/docs/test/doc2.md",
              "sourceDirName": "test",
              "slug": "/test/doc2",
              "permalink": "/docs/test/doc2",
              "draft": false,
              "editUrl": "https://github.com/facebook/docusaurus/edit/master/website/docs/test/doc2.md",
              "tags": [],
              "version": "current",
              "frontMatter": {
                "id": "doc2",
                "title": "Document Number 2"
              },
              "sidebar": "myAutogeneratedSidebar",
              "previous": {
                "title": "Style Guide",
                "permalink": "/docs/test/doc1"
              },
              "next": {
                "title": "This is Document Number 3",
                "permalink": "/docs/test/doc3"
              }
            },
            {
              "unversionedId": "test/doc3",
              "id": "test/doc3",
              "title": "This is Document Number 3",
              "description": "Lorem ipsum dolor sit amet, consectetur adipiscing elit. In ac euismod odio, eu consequat dui. Nullam molestie consectetur risus id imperdiet. Proin sodales ornare turpis, non mollis massa ultricies id. Nam at nibh scelerisque, feugiat ante non, dapibus tortor. Vivamus volutpat diam quis tellus elementum bibendum. Praesent semper gravida velit quis aliquam. Etiam in cursus neque. Nam lectus ligula, malesuada et mauris a, bibendum faucibus mi. Phasellus ut interdum felis. Phasellus in odio pulvinar, porttitor urna eget, fringilla lectus. Aliquam sollicitudin est eros. Mauris consectetur quam vitae mauris interdum hendrerit. Lorem ipsum dolor sit amet, consectetur adipiscing elit.",
              "source": "@site/docs/test/doc3.md",
              "sourceDirName": "test",
              "slug": "/test/doc3",
              "permalink": "/docs/test/doc3",
              "draft": false,
              "editUrl": "https://github.com/facebook/docusaurus/edit/master/website/docs/test/doc3.md",
              "tags": [],
              "version": "current",
              "frontMatter": {
                "id": "doc3",
                "title": "This is Document Number 3"
              },
              "sidebar": "myAutogeneratedSidebar",
              "previous": {
                "title": "Document Number 2",
                "permalink": "/docs/test/doc2"
              },
              "next": {
                "title": "Powered by MDX",
                "permalink": "/docs/test/mdx"
              }
            },
            {
              "unversionedId": "test/mdx",
              "id": "test/mdx",
              "title": "Powered by MDX",
              "description": "You can write JSX and use React components within your Markdown thanks to MDX.",
              "source": "@site/docs/test/mdx.md",
              "sourceDirName": "test",
              "slug": "/test/mdx",
              "permalink": "/docs/test/mdx",
              "draft": false,
              "editUrl": "https://github.com/facebook/docusaurus/edit/master/website/docs/test/mdx.md",
              "tags": [],
              "version": "current",
              "frontMatter": {
                "id": "mdx",
                "title": "Powered by MDX"
              },
              "sidebar": "myAutogeneratedSidebar",
              "previous": {
                "title": "This is Document Number 3",
                "permalink": "/docs/test/doc3"
              },
              "next": {
                "title": "Powered by MDX",
                "permalink": "/docs/test/mdx3"
              }
            },
            {
              "unversionedId": "test/mdx3",
              "id": "test/mdx3",
              "title": "Powered by MDX",
              "description": "You can write JSX and use React components within your Markdown thanks to MDX.",
              "source": "@site/docs/test/mdx_2.md",
              "sourceDirName": "test",
              "slug": "/test/mdx3",
              "permalink": "/docs/test/mdx3",
              "draft": false,
              "editUrl": "https://github.com/facebook/docusaurus/edit/master/website/docs/test/mdx_2.md",
              "tags": [],
              "version": "current",
              "frontMatter": {
                "id": "mdx3",
                "title": "Powered by MDX"
              },
              "sidebar": "myAutogeneratedSidebar",
              "previous": {
                "title": "Powered by MDX",
                "permalink": "/docs/test/mdx"
              }
            }
          ],
          "drafts": [],
          "sidebars": {
            "myAutogeneratedSidebar": [
              {
                "type": "category",
                "label": "IIT",
                "collapsible": true,
                "collapsed": true,
                "items": [
                  {
                    "type": "doc",
                    "id": "IIT/doc1",
                    "label": "Intro"
                  },
                  {
                    "type": "doc",
                    "id": "IIT/doc2",
                    "label": "IIT on EEG"
                  },
                  {
                    "type": "doc",
                    "id": "IIT/doc3",
                    "label": "IIT on fMRI"
                  }
                ]
              },
              {
                "type": "category",
                "label": "Quaddle2.0",
                "collapsible": true,
                "collapsed": true,
                "items": [
                  {
                    "type": "doc",
                    "id": "Quaddle2.0/quaddle_01",
                    "label": "Intro & Download"
                  },
                  {
                    "type": "doc",
                    "id": "Quaddle2.0/quaddle_02",
                    "label": "Get Start"
                  },
                  {
                    "type": "doc",
                    "id": "Quaddle2.0/quaddle_03",
                    "label": "Troubleshooting"
                  },
                  {
                    "type": "doc",
                    "id": "Quaddle2.0/quaddle_04",
                    "label": "Adding Dimension"
                  },
                  {
                    "type": "doc",
                    "id": "Quaddle2.0/quaddle_05",
                    "label": "Quaddle Dimensions"
                  }
                ]
              },
              {
                "type": "category",
                "label": "Sequence Learning",
                "collapsible": true,
                "collapsed": true,
                "items": [
                  {
                    "type": "doc",
                    "id": "Sequence Learning/SL_Intro",
                    "label": "Intro"
                  }
                ]
              },
              {
                "type": "category",
                "label": "test",
                "collapsible": true,
                "collapsed": true,
                "items": [
                  {
                    "type": "doc",
                    "id": "test/doc1",
                    "label": "Style Guide"
                  },
                  {
                    "type": "doc",
                    "id": "test/doc2"
                  },
                  {
                    "type": "doc",
                    "id": "test/doc3"
                  },
                  {
                    "type": "doc",
                    "id": "test/mdx"
                  },
                  {
                    "type": "doc",
                    "id": "test/mdx3"
                  }
                ]
              }
            ]
          }
        }
      ]
    }
  },
  "docusaurus-plugin-content-blog": {
    "default": {
      "blogSidebarTitle": "Recent posts",
      "blogPosts": [
        {
          "id": "welcome-docusaurus-v2",
          "metadata": {
            "permalink": "/blog/welcome-docusaurus-v2",
            "source": "@site/blog/2019-09-05-hello-docusaurus-v2.md",
            "title": "Welcome Docusaurus v2 🔬",
            "description": "This is my first post on Docusaurus 2.",
            "date": "2021-09-30T10:00:00.000Z",
            "formattedDate": "September 30, 2021",
            "tags": [
              {
                "label": "hello",
                "permalink": "/blog/tags/hello"
              },
              {
                "label": "docusaurus-v2",
                "permalink": "/blog/tags/docusaurus-v-2"
              }
            ],
            "readingTime": 0.135,
            "hasTruncateMarker": true,
            "authors": [
              {
                "name": "Joel Marcey",
                "title": "Co-creator of Docusaurus 1",
                "url": "https://github.com/JoelMarcey",
                "image_url": "https://github.com/JoelMarcey.png",
                "imageURL": "https://github.com/JoelMarcey.png"
              },
              {
                "name": "Sébastien Lorber",
                "title": "Docusaurus maintainer",
                "url": "https://sebastienlorber.com",
                "image_url": "https://github.com/slorber.png",
                "email": "jimarcey@gmail.com",
                "imageURL": "https://github.com/slorber.png"
              }
            ],
            "frontMatter": {
              "title": "Welcome Docusaurus v2 🔬",
              "description": "This is my first post on Docusaurus 2.",
              "slug": "welcome-docusaurus-v2",
              "authors": [
                {
                  "name": "Joel Marcey",
                  "title": "Co-creator of Docusaurus 1",
                  "url": "https://github.com/JoelMarcey",
                  "image_url": "https://github.com/JoelMarcey.png",
                  "imageURL": "https://github.com/JoelMarcey.png"
                },
                {
                  "name": "Sébastien Lorber",
                  "title": "Docusaurus maintainer",
                  "url": "https://sebastienlorber.com",
                  "image_url": "https://github.com/slorber.png",
                  "email": "jimarcey@gmail.com",
                  "imageURL": "https://github.com/slorber.png"
                }
              ],
              "tags": [
                "hello",
                "docusaurus-v2"
              ],
              "image": "https://i.imgur.com/mErPwqL.png",
              "hide_table_of_contents": false,
              "date": "2021-09-30T10:00"
            }
          },
          "content": "Welcome to this blog. This blog is created with [**Docusaurus 2**](https://docusaurus.io/).\n\n<!--truncate-->\n\nThis is my first post on Docusaurus 2.\n\nA whole bunch of exploration to follow."
        }
      ],
      "blogListPaginated": [
        {
          "items": [
            "welcome-docusaurus-v2"
          ],
          "metadata": {
            "permalink": "/blog",
            "page": 1,
            "postsPerPage": 10,
            "totalPages": 1,
            "totalCount": 1,
            "blogDescription": "Blog",
            "blogTitle": "Blog"
          }
        }
      ],
      "blogTags": {
        "/blog/tags/hello": {
          "label": "hello",
          "items": [
            "welcome-docusaurus-v2"
          ],
          "permalink": "/blog/tags/hello",
          "pages": [
            {
              "items": [
                "welcome-docusaurus-v2"
              ],
              "metadata": {
                "permalink": "/blog/tags/hello",
                "page": 1,
                "postsPerPage": 10,
                "totalPages": 1,
                "totalCount": 1,
                "blogDescription": "Blog",
                "blogTitle": "Blog"
              }
            }
          ]
        },
        "/blog/tags/docusaurus-v-2": {
          "label": "docusaurus-v2",
          "items": [
            "welcome-docusaurus-v2"
          ],
          "permalink": "/blog/tags/docusaurus-v-2",
          "pages": [
            {
              "items": [
                "welcome-docusaurus-v2"
              ],
              "metadata": {
                "permalink": "/blog/tags/docusaurus-v-2",
                "page": 1,
                "postsPerPage": 10,
                "totalPages": 1,
                "totalCount": 1,
                "blogDescription": "Blog",
                "blogTitle": "Blog"
              }
            }
          ]
        }
      },
      "blogTagsListPath": "/blog/tags"
    }
  },
  "docusaurus-plugin-content-pages": {
    "default": [
      {
        "type": "jsx",
        "permalink": "/",
        "source": "@site/src/pages/index.js"
      }
    ]
  },
  "docusaurus-plugin-debug": {},
  "docusaurus-theme-classic": {},
  "docusaurus-theme-live-codeblock": {},
  "docusaurus-bootstrap-plugin": {},
  "docusaurus-mdx-fallback-plugin": {}
}